snapshot_testing/__init__.py
snapshot_testing/py.typed
snapshot_testing/snapshot.py
snapshot_testing-0.1.0.dist-info/METADATA
snapshot_testing-0.1.0.dist-info/WHEEL
snapshot_testing-0.1.0.dist-info/top_level.txt
snapshot_testing-0.1.0.dist-info/RECORD
