Metadata-Version: 2.4
Name: snapshot-testing
Version: 0.1.0
Summary: Add your description here
Author-email: Niels Neerhoff <nielsneerhoff@gmail.com>
Requires-Python: >=3.13
Requires-Dist: pytest
